setup.py
djbehave/__init__.py
djbehave/loader.py
djbehave/models.py
djbehave/runner.py
djbehave.egg-info/PKG-INFO
djbehave.egg-info/SOURCES.txt
djbehave.egg-info/dependency_links.txt
djbehave.egg-info/requires.txt
djbehave.egg-info/top_level.txt
djbehave/management/__init__.py
djbehave/management/commands/__init__.py
djbehave/management/commands/behave.py
djbehave/server/__init__.py
djbehave/server/base.py
djbehave/server/command.py
djbehave/server/resource.py